{
	"version": "0.2",
	"ignorePaths": [
		"**/*.example",
		"**/i18n/resources/es.json",
		"**/i18n/resources/zh.json"
	],
	"dictionaryDefinitions": [],
	"dictionaries": [],
	"words": [
		"activedescendant",
		"autofocus",
		"backgrounded",
		"behaviour",
		"btrim",
		"bytea",
		"callability",
		"callback",
		"castsite",
		"Colocating",
		"combinators",
		"commitlint",
		"Contentful",
		"contravariance",
		"DISTRO",
		"dotenv",
		"elif",
		"ENOENT",
		"Español",
		"euxo",
		"fkey",
		"focusable",
		"healthcheck",
		"Hono",
		"hoverable",
		"isnan",
		"lntp",
		"mdfind",
		"mstone",
		"mysongshare",
		"networkidle",
		"njsproj",
		"nohup",
		"nonconstructor",
		"noninteractive",
		"nonoctal",
		"ntvs",
		"oxfmt",
		"oxfmtrc",
		"oxlint",
		"oxlintrc",
		"parseable",
		"partialization",
		"partialize",
		"PGDATABASE",
		"pgdg",
		"PGHOST",
		"PGPASSWORD",
		"PGPORT",
		"PGRST",
		"PGUSER",
		"pidfile",
		"pipefail",
		"pkey",
		"plpgsql",
		"Postgrest",
		"Prefs",
		"prehydrate",
		"psql",
		"recognise",
		"setsid",
		"sonarjs",
		"songshare",
		"Supabase",
		"suspendable",
		"tabindex",
		"thenables",
		"timestamptz",
		"trivago",
		"uninvoked",
		"viewports",
		"Vite",
		"Vitest",
		"wagoid",
		"WCAG",
		"xmloption"
	],
	"ignoreWords": [],
	"import": []
}
